crude.py
crude_orm-1.0.3.dist-info/LICENSE
crude_orm-1.0.3.dist-info/METADATA
crude_orm-1.0.3.dist-info/WHEEL
crude_orm-1.0.3.dist-info/top_level.txt
crude_orm-1.0.3.dist-info/RECORD
