Metadata-Version: 2.1
Name: crude-orm
Version: 1.0.3
Summary: A descriptive ORM for Python
Home-page: https://crudepy.org
Author: Kristoffer A. Wright
Author-email: kris.al.wright@gmail.com
License: MIT
Project-URL: Source, https://github.com/kawright/crude
Platform: any
Classifier: Development Status :: 4 - Beta
Classifier: Programming Language :: Python :: 3
Classifier: License :: OSI Approved :: MIT License
Classifier: Operating System :: OS Independent
Classifier: Intended Audience :: Developers
Classifier: Intended Audience :: System Administrators
Classifier: Topic :: Database
Classifier: Topic :: Software Development
License-File: LICENSE
